ApiTools_fsdjfoi/__init__.py
ApiTools_fsdjfoi/api.py
ApiTools_fsdjfoi/config.py
ApiTools_fsdjfoi/model.py
ApiTools_fsdjfoi/os_custom.py
ApiTools_fsdjfoi/pillow_custom.py
ApiTools_fsdjfoi-0.2.dist-info/METADATA
ApiTools_fsdjfoi-0.2.dist-info/WHEEL
ApiTools_fsdjfoi-0.2.dist-info/top_level.txt
ApiTools_fsdjfoi-0.2.dist-info/RECORD
