Metadata-Version: 2.1
Name: ApiTools-fsdjfoi
Version: 0.2
Summary: Description of your library
Home-page: https://github.com/yourusername/yourrepository
Author: Your Name
Author-email: your@email.com
Requires-Dist: annotated-types ==0.6.0
Requires-Dist: anyio ==4.3.0
Requires-Dist: certifi ==2024.2.2
Requires-Dist: charset-normalizer ==3.3.2
Requires-Dist: contourpy ==1.2.0
Requires-Dist: cycler ==0.12.1
Requires-Dist: exceptiongroup ==1.2.0
Requires-Dist: fastapi ==0.110.0
Requires-Dist: filelock ==3.9.0
Requires-Dist: fonttools ==4.50.0
Requires-Dist: fsspec ==2023.4.0
Requires-Dist: idna ==3.6
Requires-Dist: Jinja2 ==3.1.2
Requires-Dist: kiwisolver ==1.4.5
Requires-Dist: MarkupSafe ==2.1.3
Requires-Dist: matplotlib ==3.8.3
Requires-Dist: mpmath ==1.3.0
Requires-Dist: networkx ==3.2.1
Requires-Dist: numpy ==1.26.3
Requires-Dist: opencv-python ==4.9.0.80
Requires-Dist: packaging ==24.0
Requires-Dist: pandas ==2.2.1
Requires-Dist: pillow ==10.2.0
Requires-Dist: psutil ==5.9.8
Requires-Dist: py-cpuinfo ==9.0.0
Requires-Dist: pydantic ==2.6.4
Requires-Dist: pydantic-core ==2.16.3
Requires-Dist: pyparsing ==3.1.2
Requires-Dist: python-dateutil ==2.9.0.post0
Requires-Dist: pytz ==2024.1
Requires-Dist: PyYAML ==6.0.1
Requires-Dist: requests ==2.31.0
Requires-Dist: scipy ==1.12.0
Requires-Dist: seaborn ==0.13.2
Requires-Dist: six ==1.16.0
Requires-Dist: sniffio ==1.3.1
Requires-Dist: starlette ==0.36.3
Requires-Dist: sympy ==1.12
Requires-Dist: thop ==0.1.1.post2209072238
Requires-Dist: tqdm ==4.66.2
Requires-Dist: typing-extensions ==4.8.0
Requires-Dist: tzdata ==2024.1
Requires-Dist: ultralytics ==8.1.30
Requires-Dist: urllib3 ==2.2.1
